[
  {
    "keyword": "Feature",
    "name": "On Amazon Search for product add to basket and check basket total",
    "line": 1,
    "id": "on-amazon-search-for-product-add-to-basket-and-check-basket-total",
    "tags": [],
    "uri": "featureFiles\\addItemToCart.feature",
    "elements": [
      {
        "id": "on-amazon-search-for-product-add-to-basket-and-check-basket-total;search-for-product-add-to-basket",
        "keyword": "Scenario",
        "line": 12,
        "name": "Search for product add to basket",
        "tags": [],
        "type": "scenario",
        "steps": [
          {
            "arguments": [],
            "keyword": "Given ",
            "line": 4,
            "name": "Amazon.co.uk is open",
            "match": {
              "location": "stepDef\\addItemToCart.steps.js:14"
            },
            "result": {
              "status": "passed",
              "duration": 6492000000
            }
          },
          {
            "arguments": [],
            "keyword": "When ",
            "line": 5,
            "name": "I click Sign-in",
            "match": {
              "location": "stepDef\\addItemToCart.steps.js:18"
            },
            "result": {
              "status": "passed",
              "duration": 1540000000
            }
          },
          {
            "arguments": [],
            "keyword": "And ",
            "line": 6,
            "name": "enter valid 'username' as 'rkkiran2020@gmail.com'",
            "match": {
              "location": "stepDef\\addItemToCart.steps.js:21"
            },
            "result": {
              "status": "passed",
              "duration": 226000000
            }
          },
          {
            "arguments": [],
            "keyword": "And ",
            "line": 7,
            "name": "I 'Continue'",
            "match": {
              "location": "stepDef\\addItemToCart.steps.js:24"
            },
            "result": {
              "status": "passed",
              "duration": 3000000
            }
          },
          {
            "arguments": [],
            "keyword": "And ",
            "line": 8,
            "name": "enter valid 'password' as 'ITGpassw0rd'",
            "match": {
              "location": "stepDef\\addItemToCart.steps.js:21"
            },
            "result": {
              "status": "passed",
              "duration": 1329000000
            }
          },
          {
            "arguments": [],
            "keyword": "And ",
            "line": 9,
            "name": "I 'signed in'",
            "match": {
              "location": "stepDef\\addItemToCart.steps.js:24"
            },
            "result": {
              "status": "passed",
              "duration": 2000000
            }
          },
          {
            "arguments": [],
            "keyword": "Then ",
            "line": 10,
            "name": "I am logged in",
            "match": {
              "location": "stepDef\\addItemToCart.steps.js:29"
            },
            "result": {
              "status": "passed",
              "duration": 5063000000
            }
          },
          {
            "arguments": [],
            "keyword": "Given ",
            "line": 13,
            "name": "when I search for 'iceworks 5000'",
            "match": {
              "location": "stepDef\\addItemToCart.steps.js:34"
            },
            "result": {
              "status": "passed",
              "duration": 2642000000
            }
          },
          {
            "arguments": [],
            "keyword": "When ",
            "line": 14,
            "name": "the search results are displayed",
            "match": {
              "location": "stepDef\\addItemToCart.steps.js:37"
            },
            "result": {
              "status": "passed",
              "duration": 70000000
            }
          },
          {
            "arguments": [],
            "keyword": "Then ",
            "line": 15,
            "name": "the search results has the 'iceworks 5000' in it",
            "match": {
              "location": "stepDef\\addItemToCart.steps.js:41"
            },
            "result": {
              "status": "passed",
              "duration": 2356000000
            }
          },
          {
            "arguments": [],
            "keyword": "Given ",
            "line": 16,
            "name": "I add \"iceworks 5000\" to my basket",
            "match": {
              "location": "stepDef\\addItemToCart.steps.js:44"
            },
            "result": {
              "status": "passed",
              "duration": 5380000000
            }
          },
          {
            "arguments": [],
            "keyword": "When ",
            "line": 17,
            "name": "I check my basket total",
            "match": {
              "location": "stepDef\\addItemToCart.steps.js:49"
            },
            "result": {
              "status": "passed",
              "duration": 1528000000
            }
          },
          {
            "arguments": [],
            "keyword": "Then ",
            "line": 18,
            "name": "it should match the price of the item added into basket",
            "match": {
              "location": "stepDef\\addItemToCart.steps.js:54"
            },
            "result": {
              "status": "passed",
              "duration": 1000000
            }
          },
          {
            "keyword": "After",
            "hidden": true,
            "match": {
              "location": "node_modules\\protractor-cucumber-framework\\lib\\resultsCapturer.js:27"
            },
            "result": {
              "status": "passed",
              "duration": 1000000
            }
          }
        ]
      }
    ]
  }
]